{
    "Title": "Conditions of acceptance",
    "LinkTitle": "Conditions of acceptance",
    "DisplayType": "Pages",
    "Pages": [
        {
            "PageId": "999999",
            "SequenceId": null,
            "SectionId": null,
            "Title": "Conditions of acceptance",
            "LinkTitle": "",
            "InfoText": "",
            "Questions": [
                {
                    "QuestionId": "COA-1",
                    "QuestionTag": "COAStage1Application",
                    "Label": "",
                    "ShortLabel": "",
                    "QuestionBodyText": "",
                    "Hint": "",
                    "Input": {
                        "Type": "Text",
                        "Validations": []
                    }
                }
            ],
			"PageOfAnswers": [],
            "Next": [
                {
                    "Action": "ReturnToSection",
                    "ReturnId": "",
                    "Conditions": []
                }
            ],
            "AllowMultipleAnswers": false,
            "Active": true,
            "NotRequiredConditions": [],
            "ActivatedByPageId": null,
            "BodyText": ""
        }
    ]
}